{
  "SoloEvent_Saru": {
    "dateStart": "2021-05-31T07:00:00Z",
    "dateEnd": "2021-06-07T07:00:00Z",
    "newsType": "Event",
    "newsHeadline": "News_SoloEvent_Generic_Headline",
    "newsName": "UI_Events_SoloEvent_Title",
    "newsShortDesc": "UI_Events_SoloEvent_Desc",
    "backgroundPrefab": "SoloEvent_Background",
    "thumbnailImage": "SoloEvent_Saru",
    "characterId": "Saru",
    "id": "SoloEvent_Saru"
  },
  "SoloEvent_Dukat": {
    "dateStart": "2021-05-17T07:00:00Z",
    "dateEnd": "2021-05-24T07:00:00Z",
    "newsType": "Event",
    "newsHeadline": "News_SoloEvent_Generic_Headline",
    "newsName": "UI_Events_SoloEvent_Title",
    "newsShortDesc": "UI_Events_SoloEvent_Desc",
    "backgroundPrefab": "SoloEvent_Background",
    "thumbnailImage": "Dukat_Portrait",
    "characterId": "Dukat",
    "id": "SoloEvent_Dukat"
  },
  "SoloEvent_Nine": {
    "dateStart": "2021-05-24T07:00:00Z",
    "dateEnd": "2021-05-31T07:00:00Z",
    "newsType": "Event",
    "newsHeadline": "News_SoloEvent_Generic_Headline",
    "newsName": "UI_Events_SoloEvent_Title",
    "newsShortDesc": "UI_Events_SoloEvent_Desc",
    "backgroundPrefab": "SoloEvent_Background",
    "thumbnailImage": "Nine_Portrait",
    "characterId": "Nine",
    "id": "SoloEvent_Nine"
  },
  "SoloEvent_Phlox": {
    "dateStart": "2021-05-31T07:00:00Z",
    "dateEnd": "2021-06-07T07:00:00Z",
    "newsType": "Event",
    "newsHeadline": "News_SoloEvent_Generic_Headline",
    "newsName": "UI_Events_SoloEvent_Title",
    "newsShortDesc": "UI_Events_SoloEvent_Desc",
    "backgroundPrefab": "SoloEvent_Background",
    "thumbnailImage": "Phlox_Portrait",
    "characterId": "Phlox",
    "id": "SoloEvent_Phlox"
  },
  "NewCharacter_PicardDixon": {
    "dateStart": "2021-06-14T07:00:00Z",
    "dateEnd": "2021-06-21T07:00:00Z",
    "newsType": "Character",
    "newsHeadline": "News_Crew_Generic_Headline",
    "newsName": "Common_PicardDixon",
    "newsShortDesc": "Data_Character_PicardDixon_description",
    "backgroundPrefab": "NewCharacter_Background",
    "thumbnailImage": "NewCharacter_PicardDixon",
    "characterId": "PicardDixon",
    "id": "NewCharacter_PicardDixon"
  },
  "SoloEvent_PicardDixon": {
    "dateStart": "2021-06-14T07:00:00Z",
    "dateEnd": "2021-06-21T07:00:00Z",
    "newsType": "Event",
    "newsHeadline": "News_SoloEvent_Generic_Headline",
    "newsName": "UI_Events_PicardWeek_Title",
    "newsShortDesc": "UI_Events_PicardWeek_Desc",
    "backgroundPrefab": "SoloEvent_Background",
    "thumbnailImage": "SoloEvent_PicardDixon",
    "characterId": "PicardDixon",
    "eventReference": "Event_Solo_PicardDixon_01",
    "id": "SoloEvent_PicardDixon"
  },
  "NewCharacter_Stamets": {
    "dateStart": "2021-06-21T07:00:00Z",
    "dateEnd": "2021-06-28T07:00:00Z",
    "newsType": "Character",
    "newsHeadline": "News_Crew_Generic_Headline",
    "newsName": "Common_Stamets",
    "newsShortDesc": "Data_Character_Stamets_description",
    "backgroundPrefab": "NewCharacter_Background",
    "thumbnailImage": "NewCharacter_Stamets",
    "characterId": "Stamets",
    "id": "NewCharacter_Stamets"
  },
  "SoloEvent_Stamets": {
    "dateStart": "2021-06-21T07:00:00Z",
    "dateEnd": "2021-06-28T07:00:00Z",
    "newsType": "Event",
    "newsHeadline": "News_SoloEvent_Generic_Headline",
    "newsName": "UI_Events_SoloEvent_Title",
    "newsShortDesc": "UI_Events_StametsPride_Desc",
    "backgroundPrefab": "SoloEvent_Background",
    "thumbnailImage": "SoloEvent_Stamets",
    "characterId": "Stamets",
    "eventReference": "Event_Solo_Stamets_01",
    "id": "SoloEvent_Stamets"
  },
  "FactionEvent_FedKling_RikerMartok": {
    "dateStart": "2021-06-28T07:00:00Z",
    "dateEnd": "2021-07-05T07:00:00Z",
    "newsType": "Event",
    "newsHeadline": "News_FactionEvent_Generic_Headline",
    "newsName": "Events_FactionEvent_FedKling_Title",
    "newsShortDesc": "Events_FactionEvent_FedKling_Desc",
    "backgroundPrefab": "FactionEvent_Background",
    "thumbnailImage": "FactionEvent_Thumbnail",
    "characterId": "Riker",
    "characterId2": "Martok",
    "eventReference": "Event_Faction_FedKling_RikerMartok_01",
    "id": "FactionEvent_FedKling_RikerMartok"
  },
  "SoloEvent_McCoy": {
    "dateStart": "2021-07-05T07:00:00Z",
    "dateEnd": "2021-07-12T07:00:00Z",
    "newsType": "Event",
    "newsHeadline": "News_SoloEvent_Generic_Headline",
    "newsName": "UI_Events_SoloEvent_Title",
    "newsShortDesc": "UI_Events_SoloEvent_Desc",
    "backgroundPrefab": "SoloEvent_Background",
    "thumbnailImage": "SoloEvent_McCoy",
    "characterId": "McCoy",
    "eventReference": "Event_Solo_McCoy_01",
    "id": "SoloEvent_McCoy"
  },
  "NewCharacter_Tilly": {
    "dateStart": "2021-07-12T07:00:00Z",
    "dateEnd": "2021-07-19T07:00:00Z",
    "newsType": "Character",
    "newsHeadline": "News_Crew_Generic_Headline",
    "newsName": "Common_Tilly",
    "newsShortDesc": "Data_Character_Tilly_description",
    "backgroundPrefab": "NewCharacter_Background",
    "thumbnailImage": "NewCharacter_Tilly",
    "characterId": "Tilly",
    "id": "NewCharacter_Tilly"
  },
  "SoloEvent_Tilly": {
    "dateStart": "2021-07-12T07:00:00Z",
    "dateEnd": "2021-07-19T07:00:00Z",
    "newsType": "Event",
    "newsHeadline": "News_SoloEvent_Generic_Headline",
    "newsName": "UI_Events_SoloEvent_Title",
    "newsShortDesc": "UI_Events_SoloEvent_Desc",
    "backgroundPrefab": "SoloEvent_Background",
    "thumbnailImage": "SoloEvent_Tilly",
    "characterId": "Tilly",
    "eventReference": "Event_Solo_Tilly_01",
    "id": "SoloEvent_Tilly"
  },
  "FactionEvent_FedRomu_PicardTomalak": {
    "dateStart": "2021-07-19T07:00:00Z",
    "dateEnd": "2021-07-26T07:00:00Z",
    "newsType": "Event",
    "newsHeadline": "News_FactionEvent_Generic_Headline",
    "newsName": "Events_FactionEvent_FedRomu_Title",
    "newsShortDesc": "Events_FactionEvent_FedRomu_Desc",
    "backgroundPrefab": "FactionEvent_Background",
    "thumbnailImage": "FactionEvent_Thumbnail",
    "characterId": "Picard",
    "characterId2": "Tomalak",
    "eventReference": "Event_Faction_FedKling_RikerMartok_01",
    "id": "FactionEvent_FedRomu_PicardTomalak"
  },
  "NewCharacter_Chang": {
    "dateStart": "2021-07-26T07:00:00Z",
    "dateEnd": "2021-08-02T07:00:00Z",
    "newsType": "Event",
    "newsHeadline": "News_SoloEvent_Generic_Headline",
    "newsName": "UI_Events_SoloEvent_Title",
    "newsShortDesc": "UI_Events_SoloEvent_Desc",
    "backgroundPrefab": "SoloEvent_Background",
    "thumbnailImage": "SoloEvent_Chang",
    "characterId": "Chang",
    "id": "NewCharacter_Chang"
  },
  "SoloEvent_Chang": {
    "dateStart": "2021-07-26T07:00:00Z",
    "dateEnd": "2021-08-02T07:00:00Z",
    "newsType": "Event",
    "newsHeadline": "News_SoloEvent_Generic_Headline",
    "newsName": "UI_Events_SoloEvent_Title",
    "newsShortDesc": "UI_Events_SoloEvent_Desc",
    "backgroundPrefab": "SoloEvent_Background",
    "thumbnailImage": "SoloEvent_Chang",
    "characterId": "Chang",
    "eventReference": "Event_Solo_Chang_01",
    "id": "SoloEvent_Chang"
  },
  "SoloEvent_Locutus": {
    "dateStart": "2021-08-02T07:00:00Z",
    "dateEnd": "2021-08-09T07:00:00Z",
    "newsType": "Event",
    "newsHeadline": "News_SoloEvent_Generic_Headline",
    "newsName": "UI_Events_SoloEvent_Title",
    "newsShortDesc": "UI_Events_SoloEvent_Desc",
    "backgroundPrefab": "SoloEvent_Background",
    "thumbnailImage": "SoloEvent_Locutus",
    "characterId": "Locutus",
    "eventReference": "Event_Solo_Locutus_01",
    "id": "SoloEvent_Locutus"
  },
  "NewCharacter_Elnor": {
    "dateStart": "2021-08-09T07:00:00Z",
    "dateEnd": "2021-08-16T07:00:00Z",
    "newsType": "Event",
    "newsHeadline": "News_SoloEvent_Generic_Headline",
    "newsName": "UI_Events_SoloEvent_Title",
    "newsShortDesc": "UI_Events_SoloEvent_Desc",
    "backgroundPrefab": "SoloEvent_Background",
    "thumbnailImage": "SoloEvent_Elnor",
    "characterId": "Elnor",
    "id": "NewCharacter_Elnor"
  },
  "SoloEvent_Elnor": {
    "dateStart": "2021-08-09T07:00:00Z",
    "dateEnd": "2021-08-16T07:00:00Z",
    "newsType": "Event",
    "newsHeadline": "News_SoloEvent_Generic_Headline",
    "newsName": "UI_Events_SoloEvent_Title",
    "newsShortDesc": "UI_Events_SoloEvent_Desc",
    "backgroundPrefab": "SoloEvent_Background",
    "thumbnailImage": "SoloEvent_Elnor",
    "characterId": "Elnor",
    "eventReference": "Event_Solo_Chang_01",
    "id": "SoloEvent_Elnor"
  },
  "SeasonStart_01": {
    "dateStart": "2021-07-12T07:00:00Z",
    "dateEnd": "2021-07-26T07:00:00Z",
    "newsType": 5,
    "newsHeadline": "News_Seasons_Generic_Headline",
    "newsName": "News_Seasons_Generic_Name",
    "newsShortDesc": "News_Seasons_Generic_Desc",
    "backgroundPrefab": "Seasons_Background",
    "thumbnailImage": "BG_PVP_Seasons_07_Small",
    "id": "SeasonStart_01"
  },
  "SeasonStart_02": {
    "dateStart": "2021-07-26T07:00:00Z",
    "dateEnd": "2021-08-09T07:00:00Z",
    "newsType": 5,
    "newsHeadline": "News_Seasons_Generic_Headline",
    "newsName": "News_Seasons_Generic_Name",
    "newsShortDesc": "News_Seasons_Generic_Desc",
    "backgroundPrefab": "Seasons_Background",
    "thumbnailImage": "BG_PVP_Seasons_07_Small",
    "id": "SeasonStart_02"
  },
  "SeasonStart_03": {
    "dateStart": "2021-08-09T07:00:00Z",
    "dateEnd": "2021-08-23T07:00:00Z",
    "newsType": 5,
    "newsHeadline": "News_Seasons_Generic_Headline",
    "newsName": "News_Seasons_Generic_Name",
    "newsShortDesc": "News_Seasons_Generic_Desc",
    "backgroundPrefab": "Seasons_Background",
    "thumbnailImage": "BG_PVP_Seasons_07_Small",
    "id": "SeasonStart_03"
  },
  "SeasonStart_04": {
    "dateStart": "2021-08-23T07:00:00Z",
    "dateEnd": "2021-09-06T07:00:00Z",
    "newsType": 5,
    "newsHeadline": "News_Seasons_Generic_Headline",
    "newsName": "News_Seasons_Generic_Name",
    "newsShortDesc": "News_Seasons_Generic_Desc",
    "backgroundPrefab": "Seasons_Background",
    "thumbnailImage": "BG_PVP_Seasons_07_Small",
    "id": "SeasonStart_04"
  }
}